__init__.py
nix/__init__.py
nix/gptclient/__init__.py
nix/gptclient/_gpt_client.py
nix/gptclient/_tokens_count.py
nix/gptclient/_types.py
nix/gptclient/_validate.py
nix_gpt_client-0.2.0.dist-info/LICENCE
nix_gpt_client-0.2.0.dist-info/METADATA
nix_gpt_client-0.2.0.dist-info/WHEEL
nix_gpt_client-0.2.0.dist-info/top_level.txt
nix_gpt_client-0.2.0.dist-info/RECORD
