Metadata-Version: 2.1
Name: nix-gpt-client
Version: 0.2.0
Summary: A Python library for easy interaction with the GPT API, featuring typed requests and responses.
Author-email: nks_nix <nikusunix@gmail.com>
Maintainer-email: nks_nix <nikusunix@gmail.com>
Project-URL: Homepage, https://github.com/nixnks/nix-gpt-client
Project-URL: Documentation, https://readthedocs.org
Project-URL: Repository, https://github.com/nixnks/nix-gpt-client.git
Project-URL: Changelog, https://github.com/nixnks/nix-gpt-client/CHANGELOG.md
Keywords: openai,gpt
Classifier: Programming Language :: Python
Requires-Python: >=3.11
License-File: LICENCE
Requires-Dist: openai
Requires-Dist: tiktoken
